pyupnp/__init__.py
pyupnp/device_info.py
pyupnp/soap.py
pyupnp/utils.py
pyupnp/client/__init__.py
pyupnp/client/__main__.py
pyupnp/client/client.py
pyupnp/client/device.py
pyupnp/client/main.py
pyupnp/client/parser.py
pyupnp/client/root_device.py
pyupnp/client/scpd.py
pyupnp/server/__init__.py
pyupnp/server/device.py
pyupnp/server/server.py
pyupnp/server/service.py
pyupnp/server/subscription.py
pyupnp/server/web.py
pyupnp/ssdp/__init__.py
pyupnp/ssdp/messages.py
pyupnp/ssdp/parser.py
pyupnp/ssdp/protocol.py
pyupnp/ssdp/socket.py
python_upnp-1.0.0.dist-info/entry_points.txt
python_upnp-1.0.0.dist-info/LICENSE
python_upnp-1.0.0.dist-info/WHEEL
python_upnp-1.0.0.dist-info/METADATA
python_upnp-1.0.0.dist-info/RECORD
