Metadata-Version: 2.1
Name: python-upnp
Version: 1.0.0
Summary: UPnP library in pure python
Keywords: 
Author-email: Pavel Dunaev <me@neko-dev.ru>
Requires-Python: >= 3.10
Classifier: License :: OSI Approved :: MIT License
Classifier: Operating System :: Microsoft :: Windows
Classifier: Operating System :: POSIX :: Linux
Classifier: Programming Language :: Python
Classifier: Typing :: Typed
Requires-Dist: aiohttp~=3.9.5
Requires-Dist: multidict~=6.0.5
Requires-Dist: ifaddr~=0.2.0
Requires-Dist: multicast_py~=1.0.0
Project-URL: Home, https://gitlab.neko-dev.ru/me/pyupnp
Project-URL: Issues, https://gitlab.neko-dev.ru/me/pyupnp/-/issues
Project-URL: Repository, https://gitlab.neko-dev.ru/me/pyupnp
